nshm_toshi_client/__init__.py
nshm_toshi_client/config.py
nshm_toshi_client/general_task.py
nshm_toshi_client/rupture_generation_task.py
nshm_toshi_client/strong_motion_station.py
nshm_toshi_client/task_relation.py
nshm_toshi_client/timeout_http_adapter.py
nshm_toshi_client/toshi_client_base.py
nshm_toshi_client/toshi_file.py
nshm_toshi_client/toshi_task_file.py
nshm_toshi_client-1.1.1.dist-info/METADATA
nshm_toshi_client-1.1.1.dist-info/WHEEL
nshm_toshi_client-1.1.1.dist-info/licenses/LICENSE
nshm_toshi_client-1.1.1.dist-info/RECORD
