Metadata-Version: 2.4
Name: nshm-toshi-client
Version: 1.1.1
Summary: client for toshi API
License-Expression: AGPL-3.0-or-later
License-File: LICENSE
Author: Chris B Chamberlain
Author-email: chrisbc@artisan.co.nz
Requires-Python: >=3.10,<4.0
Classifier: Development Status :: 2 - Pre-Alpha
Classifier: Intended Audience :: Developers
Classifier: Natural Language :: English
Classifier: Programming Language :: Python :: 3
Requires-Dist: async-timeout (>=4.0.2)
Requires-Dist: gql (>=4.0.0)
Requires-Dist: graphql-core (>=3.2.1)
Requires-Dist: requests (>=2.27.1)
Requires-Dist: requests-toolbelt (>=1.0.0,<2.0.0)
